autograder/__init__.py
autograder/__main__.py
autograders_cli-1.1.0.dist-info/LICENSE
autograders_cli-1.1.0.dist-info/METADATA
autograders_cli-1.1.0.dist-info/WHEEL
autograders_cli-1.1.0.dist-info/entry_points.txt
autograders_cli-1.1.0.dist-info/top_level.txt
autograders_cli-1.1.0.dist-info/RECORD
