Metadata-Version: 2.1
Name: autograders-cli
Version: 1.1.0
Summary: Autograders Command Line Interface
Home-page: https://github.com/autograders/cli/
Author: Andrés Castellanos
Author-email: andres.cv@galileo.edu
License: MIT
Project-URL: Source, https://github.com/autograders/cli/
Project-URL: Documentation, https://github.com/Autograders/cli/blob/main/README.md
Platform: UNKNOWN
Classifier: License :: OSI Approved :: MIT License
Classifier: Programming Language :: Python :: 3
Classifier: Programming Language :: Python :: 3.6
Requires-Python: >=3.6
Requires-Dist: certifi (>=2020.12.5)
Requires-Dist: chardet (>=4.0.0)
Requires-Dist: idna (>=2.10)
Requires-Dist: requests (>=2.25.1)
Requires-Dist: tabulate (>=0.8.7)
Requires-Dist: urllib3 (>=1.26.3)
